DomPilot/__init__.py
DomPilot/agent/__init__.py
DomPilot/agent/agent.py
DomPilot/agent/llm_prompt.txt
DomPilot/llm_api/__init__.py
DomPilot/llm_api/generate_response.py
DomPilot/llm_api/llm_client.py
DomPilot/schemas/__init__.py
DomPilot/schemas/finished_task_schemas.py
DomPilot/schemas/tool_call_schema.py
dompilot-0.1.1.dist-info/licenses/LICENSE
dompilot-0.1.1.dist-info/METADATA
dompilot-0.1.1.dist-info/WHEEL
dompilot-0.1.1.dist-info/top_level.txt
dompilot-0.1.1.dist-info/RECORD
