Metadata-Version: 2.4
Name: DomPilot
Version: 0.1.1
Summary: AI webscraping library powered by Playwright and LLMs
Home-page: https://github.com/TheNoobiCat/DomPilot
Author: TheNoobiCat
Author-email: 
Classifier: Programming Language :: Python :: 3
Classifier: License :: OSI Approved :: MIT License
Classifier: Operating System :: OS Independent
Requires-Python: >=3.8
License-File: LICENSE
Requires-Dist: playwright>=1.40.0
Requires-Dist: playwright-stealth
Requires-Dist: httpx
Requires-Dist: jsonschema
Dynamic: author
Dynamic: classifier
Dynamic: home-page
Dynamic: license-file
Dynamic: requires-dist
Dynamic: requires-python
Dynamic: summary
